obsidian_to_latex/__init__.py
obsidian_to_latex/document.tex
obsidian_to_latex/obsidian_path.py
obsidian_to_latex/obsidian_to_latex.py
obsidian_to_latex/process_markdown.py
obsidian_to_latex-0.1.6.dist-info/entry_points.txt
obsidian_to_latex-0.1.6.dist-info/METADATA
obsidian_to_latex-0.1.6.dist-info/WHEEL
obsidian_to_latex-0.1.6.dist-info/RECORD
